{
	"*BOLC": {
		"operation": "constante",
		"templatename": "*BOLC",
		"templatedesc": "Emmaus-connect BOLC",
		"updatedby": "mben",
		"updatedtime": "2022-09-11 17:41:38",
		"coldebug": "V",
		"data" : {
			"ligneentete" : "2",
			"colnumlot" : "A",
			"colidentifiantunique" : "B",
			"coltypemateriel" : "C",
			"colconstructeur" : "D",
			"colmodel" : "E",
			"colimei" : "F",
			"colcpu" : "G",
			"colos" : "H",
			"coltaillestockage" : "I",
			"coltailleram" : "J",
			"colbatterie" : "K",
			"colecran" : "L",
			"colecranresolution" : "M",
			"colchargeur" : "N",
			"coloperateur" : "O",
			"colstatut" : "P",
			"colremarque" : "Q",
			"colcouleur" : "R",
			"colgradeesthetique" : "S",
			"colcategorie" : "T",
			"colerreur" : "U"
			},
		"header" : {
			"ligneentete" : "N° ligne entete",
			"colnumlot" : "Numéro Lot",
			"colidentifiantunique" : "Identifiant unique",
			"coltypemateriel" : "Type matériel",
			"colconstructeur" : "Constructeur",
			"colmodel" : "Modèle",
			"colimei" : "IMEI",
			"colcpu" : "Processeur",
			"colos" : "OS",
			"coltaillestockage" : "Taille stockage",
			"coltailleram" : "RAM",
			"colbatterie" : "État Batterie",
			"colecran" : "Taille écran",
			"colecranresolution" : "Résolution",
			"colchargeur" : "Chargeur",
			"coloperateur" : "Opérateur",
			"colstatut" : "Statut",
			"colremarque" : "Commentaire",
			"colcouleur" : "Couleur",
			"colgradeesthetique" : "Grade esth.",
			"colcategorie" : "Catégorie",
			"colerreur" : "Erreur"
		}
	}
}